stitch_connect_client/__init__.py
stitch_connect_client/api_client.py
stitch_connect_client/configuration.py
stitch_connect_client/exceptions.py
stitch_connect_client/rest.py
stitch_connect_client/api/__init__.py
stitch_connect_client/api/destinations_api.py
stitch_connect_client/api/sources_api.py
stitch_connect_client/api/streams_api.py
stitch_connect_client/models/__init__.py
stitch_connect_client/models/azure_destination_form_properties.py
stitch_connect_client/models/connection_check.py
stitch_connect_client/models/connection_details.py
stitch_connect_client/models/connection_step.py
stitch_connect_client/models/connection_step_props.py
stitch_connect_client/models/connection_step_props_any_of.py
stitch_connect_client/models/connection_step_props_json_schema.py
stitch_connect_client/models/create_destination_body.py
stitch_connect_client/models/create_source_body.py
stitch_connect_client/models/destination.py
stitch_connect_client/models/destination_form_properties.py
stitch_connect_client/models/destination_report_card.py
stitch_connect_client/models/error_object.py
stitch_connect_client/models/error_object_error.py
stitch_connect_client/models/field_level_metadata.py
stitch_connect_client/models/forced_replication_method.py
stitch_connect_client/models/forced_replication_method_object.py
stitch_connect_client/models/google_analytics_source_form_properties.py
stitch_connect_client/models/google_analytics_source_form_properties_report_definitions.py
stitch_connect_client/models/hook_notification.py
stitch_connect_client/models/hook_notification_config.py
stitch_connect_client/models/metadata.py
stitch_connect_client/models/metadata_object.py
stitch_connect_client/models/mixpanel_source_form_properties.py
stitch_connect_client/models/replication_job.py
stitch_connect_client/models/s3_destination_form_properties.py
stitch_connect_client/models/salesforce_source_form_properties.py
stitch_connect_client/models/source.py
stitch_connect_client-0.6.2.dist-info/LICENSE.md
stitch_connect_client-0.6.2.dist-info/WHEEL
stitch_connect_client-0.6.2.dist-info/METADATA
stitch_connect_client-0.6.2.dist-info/RECORD
