Metadata-Version: 2.1
Name: stitch_connect_client
Version: 0.6.2
Summary: Stitch Connect
Home-page: https://github.com/NarrativeScience/stitch-connect-python
License: BSD-3-Clause
Keywords: Stitch Connect,Open API,OpenAPI-Generator
Author: Annie Xu
Author-email: axu@narrativescience.com
Requires-Python: >=3.6,<4
Classifier: Intended Audience :: Developers
Classifier: License :: OSI Approved :: BSD License
Classifier: Programming Language :: Python :: 3
Classifier: Topic :: Software Development :: Libraries :: Python Modules
Requires-Dist: certifi>=14.05.14
Requires-Dist: six>=1.10
Requires-Dist: python_dateutil>=2.5.3
Requires-Dist: setuptools>=21.0.0
Requires-Dist: urllib3>=1.15.1
